{
  "objective": "Collect 1 obsidian make 1 of each type of gold tool and catch and cook a fish.",
  "sinks": [
    "obsidian",
    "golden_pickaxe",
    "golden_axe",
    "golden_shovel",
    "golden_hoe",
    "golden_sword",
    "cooked_cod"
  ],
  "vertices": [
    {
      "id": "obsidian",
      "qty": 1,
      "item_type": "resource",
      "acquisition_dependency": "lava_source"
    },
    {
      "id": "golden_pickaxe",
      "qty": 1,
      "item_type": "tool",
      "acquisition_dependency": "none"
    },
    {
      "id": "golden_axe",
      "qty": 1,
      "item_type": "tool",
      "acquisition_dependency": "none"
    },
    {
      "id": "golden_shovel",
      "qty": 1,
      "item_type": "tool",
      "acquisition_dependency": "none"
    },
    {
      "id": "golden_hoe",
      "qty": 1,
      "item_type": "tool",
      "acquisition_dependency": "none"
    },
    {
      "id": "golden_sword",
      "qty": 1,
      "item_type": "tool",
      "acquisition_dependency": "none"
    },
    {
      "id": "cooked_cod",
      "qty": 1,
      "item_type": "item",
      "acquisition_dependency": "none"
    },
    {
      "id": "water_bucket",
      "qty": 1,
      "item_type": "item",
      "acquisition_dependency": "water_source"
    },
    {
      "id": "diamond_pickaxe",
      "qty": 1,
      "item_type": "tool",
      "acquisition_dependency": "none"
    },
    {
      "id": "gold_ingot",
      "qty": 11,
      "item_type": "item",
      "acquisition_dependency": "none"
    },
    {
      "id": "stick",
      "qty": 20,
      "item_type": "item",
      "acquisition_dependency": "none"
    },
    {
      "id": "raw_cod",
      "qty": 1,
      "item_type": "resource",
      "acquisition_dependency": "water_source"
    },
    {
      "id": "furnace",
      "qty": 1,
      "item_type": "workstation",
      "acquisition_dependency": "none"
    },
    {
      "id": "coal",
      "qty": 4,
      "item_type": "resource",
      "acquisition_dependency": "none"
    },
    {
      "id": "bucket",
      "qty": 1,
      "item_type": "item",
      "acquisition_dependency": "none"
    },
    {
      "id": "diamond",
      "qty": 3,
      "item_type": "resource",
      "acquisition_dependency": "none"
    },
    {
      "id": "crafting_table",
      "qty": 1,
      "item_type": "workstation",
      "acquisition_dependency": "none"
    },
    {
      "id": "raw_gold",
      "qty": 11,
      "item_type": "resource",
      "acquisition_dependency": "none"
    },
    {
      "id": "fishing_rod",
      "qty": 1,
      "item_type": "tool",
      "acquisition_dependency": "none"
    },
    {
      "id": "raw_iron",
      "qty": 6,
      "item_type": "resource",
      "acquisition_dependency": "none"
    },
    {
      "id": "iron_ingot",
      "qty": 6,
      "item_type": "item",
      "acquisition_dependency": "none"
    },
    {
      "id": "iron_pickaxe",
      "qty": 1,
      "item_type": "tool",
      "acquisition_dependency": "none"
    },
    {
      "id": "string",
      "qty": 2,
      "item_type": "resource",
      "acquisition_dependency": "mob"
    },
    {
      "id": "stone_pickaxe",
      "qty": 1,
      "item_type": "tool",
      "acquisition_dependency": "none"
    },
    {
      "id": "cobblestone",
      "qty": 11,
      "item_type": "resource",
      "acquisition_dependency": "none"
    },
    {
      "id": "wooden_pickaxe",
      "qty": 1,
      "item_type": "tool",
      "acquisition_dependency": "none"
    },
    {
      "id": "any_plank",
      "qty": 20,
      "item_type": "item",
      "acquisition_dependency": "none"
    },
    {
      "id": "any_log",
      "qty": 5,
      "item_type": "resource",
      "acquisition_dependency": "none"
    }
  ],
  "edges": [
    {
      "from": "water_bucket",
      "to": "obsidian",
      "type": "item_dependency",
      "qty": 1,
      "consumed": false
    },
    {
      "from": "diamond_pickaxe",
      "to": "obsidian",
      "type": "tool_dependency",
      "qty": 1,
      "consumed": false
    },
    {
      "from": "gold_ingot",
      "to": "golden_pickaxe",
      "type": "crafting_input",
      "qty": 3,
      "consumed": true
    },
    {
      "from": "stick",
      "to": "golden_pickaxe",
      "type": "crafting_input",
      "qty": 2,
      "consumed": true
    },
    {
      "from": "crafting_table",
      "to": "golden_pickaxe",
      "type": "workstation_dependency",
      "qty": 1,
      "consumed": false
    },
    {
      "from": "gold_ingot",
      "to": "golden_axe",
      "type": "crafting_input",
      "qty": 3,
      "consumed": true
    },
    {
      "from": "stick",
      "to": "golden_axe",
      "type": "crafting_input",
      "qty": 2,
      "consumed": true
    },
    {
      "from": "crafting_table",
      "to": "golden_axe",
      "type": "workstation_dependency",
      "qty": 1,
      "consumed": false
    },
    {
      "from": "gold_ingot",
      "to": "golden_shovel",
      "type": "crafting_input",
      "qty": 1,
      "consumed": true
    },
    {
      "from": "stick",
      "to": "golden_shovel",
      "type": "crafting_input",
      "qty": 2,
      "consumed": true
    },
    {
      "from": "crafting_table",
      "to": "golden_shovel",
      "type": "workstation_dependency",
      "qty": 1,
      "consumed": false
    },
    {
      "from": "gold_ingot",
      "to": "golden_hoe",
      "type": "crafting_input",
      "qty": 2,
      "consumed": true
    },
    {
      "from": "stick",
      "to": "golden_hoe",
      "type": "crafting_input",
      "qty": 2,
      "consumed": true
    },
    {
      "from": "crafting_table",
      "to": "golden_hoe",
      "type": "workstation_dependency",
      "qty": 1,
      "consumed": false
    },
    {
      "from": "gold_ingot",
      "to": "golden_sword",
      "type": "crafting_input",
      "qty": 2,
      "consumed": true
    },
    {
      "from": "stick",
      "to": "golden_sword",
      "type": "crafting_input",
      "qty": 1,
      "consumed": true
    },
    {
      "from": "crafting_table",
      "to": "golden_sword",
      "type": "workstation_dependency",
      "qty": 1,
      "consumed": false
    },
    {
      "from": "raw_cod",
      "to": "cooked_cod",
      "type": "smelting_input",
      "qty": 1,
      "consumed": true
    },
    {
      "from": "coal",
      "to": "cooked_cod",
      "type": "fuel_input",
      "qty": 1,
      "consumed": true
    },
    {
      "from": "furnace",
      "to": "cooked_cod",
      "type": "workstation_dependency",
      "qty": 1,
      "consumed": false
    },
    {
      "from": "bucket",
      "to": "water_bucket",
      "type": "crafting_input",
      "qty": 1,
      "consumed": true
    },
    {
      "from": "diamond",
      "to": "diamond_pickaxe",
      "type": "crafting_input",
      "qty": 3,
      "consumed": true
    },
    {
      "from": "stick",
      "to": "diamond_pickaxe",
      "type": "crafting_input",
      "qty": 2,
      "consumed": true
    },
    {
      "from": "crafting_table",
      "to": "diamond_pickaxe",
      "type": "workstation_dependency",
      "qty": 1,
      "consumed": false
    },
    {
      "from": "raw_gold",
      "to": "gold_ingot",
      "type": "smelting_input",
      "qty": 11,
      "consumed": true
    },
    {
      "from": "coal",
      "to": "gold_ingot",
      "type": "fuel_input",
      "qty": 2,
      "consumed": true
    },
    {
      "from": "furnace",
      "to": "gold_ingot",
      "type": "workstation_dependency",
      "qty": 1,
      "consumed": false
    },
    {
      "from": "any_plank",
      "to": "stick",
      "type": "crafting_input",
      "qty": 10,
      "consumed": true
    },
    {
      "from": "stick",
      "to": "fishing_rod",
      "type": "crafting_input",
      "qty": 3,
      "consumed": true
    },
    {
      "from": "string",
      "to": "fishing_rod",
      "type": "crafting_input",
      "qty": 2,
      "consumed": true
    },
    {
      "from": "crafting_table",
      "to": "fishing_rod",
      "type": "workstation_dependency",
      "qty": 1,
      "consumed": false
    },
    {
      "from": "cobblestone",
      "to": "furnace",
      "type": "crafting_input",
      "qty": 8,
      "consumed": true
    },
    {
      "from": "crafting_table",
      "to": "furnace",
      "type": "workstation_dependency",
      "qty": 1,
      "consumed": false
    },
    {
      "from": "iron_ingot",
      "to": "bucket",
      "type": "crafting_input",
      "qty": 3,
      "consumed": true
    },
    {
      "from": "crafting_table",
      "to": "bucket",
      "type": "workstation_dependency",
      "qty": 1,
      "consumed": false
    },
    {
      "from": "iron_pickaxe",
      "to": "diamond",
      "type": "tool_dependency",
      "qty": 1,
      "consumed": false
    },
    {
      "from": "any_plank",
      "to": "crafting_table",
      "type": "crafting_input",
      "qty": 4,
      "consumed": true
    },
    {
      "from": "iron_pickaxe",
      "to": "raw_gold",
      "type": "tool_dependency",
      "qty": 1,
      "consumed": false
    },
    {
      "from": "fishing_rod",
      "to": "raw_cod",
      "type": "tool_dependency",
      "qty": 1,
      "consumed": false
    },
    {
      "from": "raw_iron",
      "to": "iron_ingot",
      "type": "smelting_input",
      "qty": 6,
      "consumed": true
    },
    {
      "from": "coal",
      "to": "iron_ingot",
      "type": "fuel_input",
      "qty": 1,
      "consumed": true
    },
    {
      "from": "furnace",
      "to": "iron_ingot",
      "type": "workstation_dependency",
      "qty": 1,
      "consumed": false
    },
    {
      "from": "iron_ingot",
      "to": "iron_pickaxe",
      "type": "crafting_input",
      "qty": 3,
      "consumed": true
    },
    {
      "from": "stick",
      "to": "iron_pickaxe",
      "type": "crafting_input",
      "qty": 2,
      "consumed": true
    },
    {
      "from": "crafting_table",
      "to": "iron_pickaxe",
      "type": "workstation_dependency",
      "qty": 1,
      "consumed": false
    },
    {
      "from": "stone_pickaxe",
      "to": "raw_iron",
      "type": "tool_dependency",
      "qty": 1,
      "consumed": false
    },
    {
      "from": "cobblestone",
      "to": "stone_pickaxe",
      "type": "crafting_input",
      "qty": 3,
      "consumed": true
    },
    {
      "from": "stick",
      "to": "stone_pickaxe",
      "type": "crafting_input",
      "qty": 2,
      "consumed": true
    },
    {
      "from": "crafting_table",
      "to": "stone_pickaxe",
      "type": "workstation_dependency",
      "qty": 1,
      "consumed": false
    },
    {
      "from": "wooden_pickaxe",
      "to": "cobblestone",
      "type": "tool_dependency",
      "qty": 1,
      "consumed": false
    },
    {
      "from": "any_plank",
      "to": "wooden_pickaxe",
      "type": "crafting_input",
      "qty": 3,
      "consumed": true
    },
    {
      "from": "stick",
      "to": "wooden_pickaxe",
      "type": "crafting_input",
      "qty": 2,
      "consumed": true
    },
    {
      "from": "crafting_table",
      "to": "wooden_pickaxe",
      "type": "workstation_dependency",
      "qty": 1,
      "consumed": false
    },
    {
      "from": "any_log",
      "to": "any_plank",
      "type": "crafting_input",
      "qty": 5,
      "consumed": true
    },
    {
      "from": "wooden_pickaxe",
      "to": "coal",
      "type": "tool_dependency",
      "qty": 1,
      "consumed": false
    }
  ]
}
